aio_dt_protocol
