Metadata-Version: 2.1
Name: aio-dt-protocol
Version: 1.3.1
Summary: Asynchronous wrapper over Chromium browser debugger protocol.
Home-page: https://github.com/PieceOfGood/aio_dt_protocol
Author: PieceOfGood
Author-email: 78sanchezz@gmail.com
License: BSD 3-Clause
Classifier: License :: OSI Approved :: BSD License
Classifier: Programming Language :: Python :: 3.8
Classifier: Programming Language :: Python :: 3.9
Classifier: Programming Language :: Python :: 3.10
Classifier: Programming Language :: Python :: 3.11
Classifier: Programming Language :: Python :: 3.12
Classifier: Operating System :: Microsoft :: Windows
Classifier: Operating System :: POSIX
License-File: LICENSE
Requires-Dist: websockets>=10.0.0
